{
  "headers": {
    "x-content-type-options": "nosniff",
    "cf-request-id": "02b548d32d0000088fcf05e200000001",
    "cache-control": "max-age=300",
    "etag": "W/\"6d0746f26f5681f0ce16324174a6cb691226c051e60385e77172aa31d09adc1e\"",
    "strict-transport-security": "max-age=31536000",
    "set-cookie": "__cfduid=d67c198e359589a803a9db849555894271589468183; expires=Sat, 13-Jun-20 14:56:23 GMT; path=/; domain=.deno.land; HttpOnly; SameSite=Lax; Secure",
    "expires": "Thu, 14 May 2020 15:01:23 GMT",
    "x-fastly-request-id": "87111f9fddd66e4c183f94fc5dd87465b84b6bbc",
    "cf-cache-status": "DYNAMIC",
    "x-cache": "MISS, HIT",
    "date": "Thu, 14 May 2020 14:56:23 GMT",
    "source-age": "72",
    "x-timer": "S1589468183.355482,VS0,VE1",
    "x-xss-protection": "1; mode=block",
    "cf-ray": "59357731e80c088f-CDG",
    "x-cache-hits": "0, 1",
    "server": "cloudflare",
    "content-type": "application/typescript; charset=utf-8",
    "expect-ct": "max-age=604800, report-uri=\"https://report-uri.cloudflare.com/cdn-cgi/beacon/expect-ct\"",
    "x-github-request-id": "E8F0:0A70:205DD:2965A:5EBD32D5",
    "vary": "Authorization,Accept-Encoding",
    "access-control-allow-origin": "*",
    "via": "1.1 varnish (Varnish/6.0), 1.1 varnish",
    "x-frame-options": "deny",
    "x-served-by": "cache-cdg20721-CDG",
    "content-security-policy": "default-src 'none'; style-src 'unsafe-inline'; sandbox"
  },
  "url": "https://deno.land/x/checksum@1.2.0/mod.ts"
}